CHANGES.txt
LICENSE.txt
MANIFEST.in
README.txt
bootstrap.py
buildout.cfg
setup.py
src/j01/__init__.py
src/j01.rater.egg-info/PKG-INFO
src/j01.rater.egg-info/SOURCES.txt
src/j01.rater.egg-info/dependency_links.txt
src/j01.rater.egg-info/namespace_packages.txt
src/j01.rater.egg-info/not-zip-safe
src/j01.rater.egg-info/requires.txt
src/j01.rater.egg-info/top_level.txt
src/j01/rater/__init__.py
src/j01/rater/configure.zcml
src/j01/rater/fieldproperty.py
src/j01/rater/interfaces.py
src/j01/rater/jsonrpc.py
src/j01/rater/jsonrpc.zcml
src/j01/rater/rating.py
src/j01/rater/rating.zcml
src/j01/rater/schema.py
src/j01/rater/scoresystem.py
src/j01/rater/scoresystem.zcml
src/j01/rater/widget.py
src/j01/rater/widget.zcml
src/j01/rater/widget_display.pt
src/j01/rater/widget_input.pt
src/j01/rater/css/j01.rater.css
src/j01/rater/img/icons.png
src/j01/rater/img/ratingDelete.gif
src/j01/rater/img/ratingStar.gif
src/j01/rater/img/ratingStarLeft.gif
src/j01/rater/img/ratingStarRight.gif
src/j01/rater/js/j01.rater.js
src/j01/rater/less/j01.rater.less
src/j01/rater/tests/__init__.py
src/j01/rater/tests/checker.txt
src/j01/rater/tests/checker_MIGRATION_P2P3.py
src/j01/rater/tests/tests.py