Metadata-Version: 2.1
Name: j01.rater
Version: 1.0.0
Summary: Rating system with property and z3c.form based widget
Home-page: http://pypi.python.org/pypi/j01.rater
Author: Roger Ineichen
Author-email: dev@projekt01.ch
License: ZPL 2.1
Keywords: zope3 z3c j01 rating system
Platform: UNKNOWN
Classifier: Development Status :: 4 - Beta
Classifier: Environment :: Web Environment
Classifier: Intended Audience :: Developers
Classifier: License :: OSI Approved :: Zope Public License
Classifier: Programming Language :: Python
Classifier: Natural Language :: English
Classifier: Operating System :: OS Independent
Classifier: Topic :: Internet :: WWW/HTTP
Classifier: Framework :: Zope3
Provides-Extra: test
